{
  "id": "118273f8-d280-41c2-abd7-f83a51eba44a",
  "prevId": "c7073700-692b-4b66-9096-a202819756f8",
  "version": "7",
  "dialect": "postgresql",
  "tables": {
    "public.authors": {
      "name": "authors",
      "schema": "",
      "columns": {
        "id": {
          "name": "id",
          "type": "integer",
          "primaryKey": true,
          "notNull": true,
          "identity": {
            "type": "always",
            "name": "authors_id_seq",
            "schema": "public",
            "increment": "1",
            "startWith": "1",
            "minValue": "1",
            "maxValue": "2147483647",
            "cache": "1",
            "cycle": false
          }
        },
        "name": {
          "name": "name",
          "type": "varchar",
          "primaryKey": false,
          "notNull": true
        }
      },
      "indexes": {},
      "foreignKeys": {},
      "compositePrimaryKeys": {},
      "uniqueConstraints": {},
      "policies": {},
      "checkConstraints": {},
      "isRLSEnabled": false
    },
    "public.booksHistory": {
      "name": "booksHistory",
      "schema": "",
      "columns": {
        "outdatedFrom": {
          "name": "outdatedFrom",
          "type": "date",
          "primaryKey": false,
          "notNull": true,
          "default": "now()"
        },
        "id": {
          "name": "id",
          "type": "integer",
          "primaryKey": false,
          "notNull": true
        },
        "title": {
          "name": "title",
          "type": "varchar",
          "primaryKey": false,
          "notNull": true
        },
        "author": {
          "name": "author",
          "type": "integer",
          "primaryKey": false,
          "notNull": false
        },
        "publishedYear": {
          "name": "publishedYear",
          "type": "integer",
          "primaryKey": false,
          "notNull": true
        },
        "genres": {
          "name": "genres",
          "type": "genre[]",
          "primaryKey": false,
          "notNull": true
        }
      },
      "indexes": {
        "id_idx": {
          "name": "id_idx",
          "columns": [
            {
              "expression": "id",
              "isExpression": false,
              "asc": true,
              "nulls": "last"
            }
          ],
          "isUnique": false,
          "concurrently": false,
          "method": "btree",
          "with": {}
        }
      },
      "foreignKeys": {
        "booksHistory_author_authors_id_fk": {
          "name": "booksHistory_author_authors_id_fk",
          "tableFrom": "booksHistory",
          "tableTo": "authors",
          "columnsFrom": [
            "author"
          ],
          "columnsTo": [
            "id"
          ],
          "onDelete": "no action",
          "onUpdate": "no action"
        }
      },
      "compositePrimaryKeys": {},
      "uniqueConstraints": {},
      "policies": {},
      "checkConstraints": {},
      "isRLSEnabled": false
    },
    "public.books": {
      "name": "books",
      "schema": "",
      "columns": {
        "id": {
          "name": "id",
          "type": "integer",
          "primaryKey": true,
          "notNull": true,
          "identity": {
            "type": "always",
            "name": "books_id_seq",
            "schema": "public",
            "increment": "1",
            "startWith": "1",
            "minValue": "1",
            "maxValue": "2147483647",
            "cache": "1",
            "cycle": false
          }
        },
        "title": {
          "name": "title",
          "type": "varchar",
          "primaryKey": false,
          "notNull": true
        },
        "author": {
          "name": "author",
          "type": "integer",
          "primaryKey": false,
          "notNull": false
        },
        "publishedYear": {
          "name": "publishedYear",
          "type": "integer",
          "primaryKey": false,
          "notNull": true
        },
        "genres": {
          "name": "genres",
          "type": "genre[]",
          "primaryKey": false,
          "notNull": true
        }
      },
      "indexes": {},
      "foreignKeys": {
        "books_author_authors_id_fk": {
          "name": "books_author_authors_id_fk",
          "tableFrom": "books",
          "tableTo": "authors",
          "columnsFrom": [
            "author"
          ],
          "columnsTo": [
            "id"
          ],
          "onDelete": "cascade",
          "onUpdate": "no action"
        }
      },
      "compositePrimaryKeys": {},
      "uniqueConstraints": {},
      "policies": {},
      "checkConstraints": {},
      "isRLSEnabled": false
    },
    "public.ratings": {
      "name": "ratings",
      "schema": "",
      "columns": {
        "id": {
          "name": "id",
          "type": "integer",
          "primaryKey": true,
          "notNull": true,
          "identity": {
            "type": "always",
            "name": "ratings_id_seq",
            "schema": "public",
            "increment": "1",
            "startWith": "1",
            "minValue": "1",
            "maxValue": "2147483647",
            "cache": "1",
            "cycle": false
          }
        },
        "book": {
          "name": "book",
          "type": "integer",
          "primaryKey": false,
          "notNull": false
        },
        "stars": {
          "name": "stars",
          "type": "integer",
          "primaryKey": false,
          "notNull": true
        },
        "comment": {
          "name": "comment",
          "type": "text",
          "primaryKey": false,
          "notNull": false
        },
        "approved": {
          "name": "approved",
          "type": "boolean",
          "primaryKey": false,
          "notNull": false,
          "default": false
        }
      },
      "indexes": {},
      "foreignKeys": {
        "ratings_book_books_id_fk": {
          "name": "ratings_book_books_id_fk",
          "tableFrom": "ratings",
          "tableTo": "books",
          "columnsFrom": [
            "book"
          ],
          "columnsTo": [
            "id"
          ],
          "onDelete": "cascade",
          "onUpdate": "no action"
        }
      },
      "compositePrimaryKeys": {},
      "uniqueConstraints": {},
      "policies": {},
      "checkConstraints": {},
      "isRLSEnabled": false
    }
  },
  "enums": {
    "public.genre": {
      "name": "genre",
      "schema": "public",
      "values": [
        "Science Fiction",
        "Romance",
        "Personal Development",
        "Fantasy",
        "Thriller"
      ]
    }
  },
  "schemas": {},
  "sequences": {},
  "roles": {},
  "policies": {},
  "views": {},
  "_meta": {
    "columns": {},
    "schemas": {},
    "tables": {}
  }
}